measure/__init__.py
ranium_test-1.1.dist-info/DESCRIPTION.rst
ranium_test-1.1.dist-info/METADATA
ranium_test-1.1.dist-info/RECORD
ranium_test-1.1.dist-info/WHEEL
ranium_test-1.1.dist-info/metadata.json
ranium_test-1.1.dist-info/top_level.txt
