Metadata-Version: 2.0
Name: ranium-test
Version: 1.1
Summary: An example of a python package from pre-existing code
Home-page: https://github.com/dhananjay-ranium/ranium-python
Author: Dhananjay Wasekar
Author-email: dhananjay@ranium.in
License: MIT
Platform: UNKNOWN
